{
  "appid": "wxb21b0c7cbd0d792f",
  "projectname": "mini-inventory-board",
  "compileType": "miniprogram",
  "miniprogramRoot": "./",
    "cloudfunctionRoot": "./cloudfunctions/",
  "srcMiniprogramRoot": "./",
  "setting": {
    "urlCheck": false,
    "es6": true,
    "enhance": true,
    "postcss": true,
    "minified": false,
    "compileHotReLoad": true,
    "packNpmManually": false,
    "ignoreUploadUnusedFiles": true,
    "compileWorklet": false,
    "uglifyFileName": false,
    "uploadWithSourceMap": true,
    "packNpmRelationList": [],
    "minifyWXSS": true,
    "minifyWXML": true,
    "localPlugins": false,
    "disableUseStrict": false,
    "useCompilerPlugins": false,
    "condition": true,
    "swc": false,
    "disableSWC": true,
    "babelSetting": {
      "ignore": [],
      "disablePlugins": [],
      "outputPath": ""
    }
  },
  "simulatorType": "wechat",
  "simulatorPluginLibVersion": {
    "wxext14566970e7e9f62": "2.27.3"
  },
  "condition": {
    "search": {
      "list": []
    },
    "conversation": {
      "list": []
    },
    "plugin": {
      "list": []
    },
    "game": {
      "list": []
    },
    "gamePlugin": {
      "list": []
    },
    "miniprogram": {
      "list": []
    }
  },
  "packOptions": {
    "ignore": [],
    "include": []
  },
  "editorSetting": {},
  "libVersion": "3.16.1",
  "projectArchitecture": "multiPlatform"
}